polytrackermidi.py
exporters/__init__.py
exporters/midi.py
parsers/__init__.py
parsers/arps.py
parsers/chords.py
parsers/constants.py
parsers/patterns.py
parsers/project.py
polytrackermidi/__init__.py
polytrackermidi/exporters/__init__.py
polytrackermidi/exporters/midi.py
polytrackermidi/parsers/__init__.py
polytrackermidi/parsers/arps.py
polytrackermidi/parsers/chords.py
polytrackermidi/parsers/constants.py
polytrackermidi/parsers/patterns.py
polytrackermidi/parsers/project.py
polyendtracker_midi_export-0.3.2.dist-info/LICENSE.txt
polyendtracker_midi_export-0.3.2.dist-info/METADATA
polyendtracker_midi_export-0.3.2.dist-info/WHEEL
polyendtracker_midi_export-0.3.2.dist-info/entry_points.txt
polyendtracker_midi_export-0.3.2.dist-info/top_level.txt
polyendtracker_midi_export-0.3.2.dist-info/RECORD
