Metadata-Version: 2.1
Name: polyendtracker-midi-export
Version: 0.3.2
Summary: Unofficial tool that converts Polyend Tracker *.mt project and *.mtp pattern files to midi files.
Home-page: https://github.com/DataGreed/polyendtracker-midi-export
Author: Alexey Strelkov
Author-email: datagreed@gmail.com
License: MIT License
Platform: UNKNOWN
Classifier: Programming Language :: Python :: 3.9
Classifier: Operating System :: OS Independent
Requires-Python: >=3.7
License-File: LICENSE.txt
Requires-Dist: MIDIUtil (==1.2.1)
